[{"birdId":"librol2","commonName":"Lilac-breasted Roller","sciName":"Coracias caudatus"},{"birdId":"rocpig","commonName":"Rock Pigeon","sciName":"Columba livia"},{"birdId":"blhher1","commonName":"Black-headed Heron","sciName":"Ardea melanocephala"},{"birdId":"afmhar1","commonName":"African Marsh Harrier","sciName":"Circus ranivorus"},{"birdId":"afpwag1","commonName":"African Pied Wagtail","sciName":"Motacilla aguimp"},{"birdId":"litgre1","commonName":"Little Grebe","sciName":"Tachybaptus ruficollis"},{"birdId":"blbtur1","commonName":"Black-billed Turaco","sciName":"Tauraco schuettii"},{"birdId":"pibpel1","commonName":"Pink-backed Pelican","sciName":"Pelecanus rufescens"},{"birdId":"hamerk1","commonName":"Hamerkop","sciName":"Scopus umbretta"},{"birdId":"blakit1","commonName":"Black Kite","sciName":"Milvus migrans"},{"birdId":"spemou2","commonName":"Speckled Mousebird","sciName":"Colius striatus"},{"birdId":"eubeat1","commonName":"European Bee-eater","sciName":"Merops apiaster"},{"birdId":"piecro1","commonName":"Pied Crow","sciName":"Corvus albus"},{"birdId":"blfapa1","commonName":"Black-faced Apalis","sciName":"Apalis personata"},{"birdId":"chucis1","commonName":"Chubb's Cisticola","sciName":"Cisticola chubbi"},{"birdId":"blksaw1","commonName":"Black Sawwing","sciName":"Psalidoprocne pristoptera"},{"birdId":"angswa1","commonName":"Angola Swallow","sciName":"Hirundo angolensis"},{"birdId":"combul2","commonName":"Common Bulbul","sciName":"Pycnonotus barbatus"},{"birdId":"afywhe3","commonName":"Green White-eye","sciName":"Zosterops stuhlmanni"},{"birdId":"afdfly1","commonName":"African Dusky Flycatcher","sciName":"Muscicapa adusta"},{"birdId":"wheslf1","commonName":"White-eyed Slaty-Flycatcher","sciName":"Melaenornis fischeri"},{"birdId":"afrsto1","commonName":"African Stonechat","sciName":"Saxicola torquatus"},{"birdId":"regsun2","commonName":"Regal Sunbird","sciName":"Cinnyris regius"},{"birdId":"bagwea1","commonName":"Baglafecht Weaver","sciName":"Ploceus baglafecht"},{"birdId":"gyhneg1","commonName":"Gray-headed Nigrita","sciName":"Nigrita canicapillus"},{"birdId":"strsee1","commonName":"Streaky Seedeater","sciName":"Crithagra striolata"},{"birdId":"nartro1","commonName":"Narina Trogon","sciName":"Apaloderma narina"},{"birdId":"crohor1","commonName":"Crowned Hornbill","sciName":"Lophoceros alboterminatus"},{"birdId":"bawhor2","commonName":"Black-and-white-casqued Hornbill","sciName":"Bycanistes subcylindricus"},{"birdId":"ccbeat1","commonName":"Cinnamon-chested Bee-eater","sciName":"Merops oreobates"},{"birdId":"yertin1","commonName":"Yellow-rumped Tinkerbird","sciName":"Pogoniulus bilineatus"},{"birdId":"ruwbat1","commonName":"Rwenzori Batis","sciName":"Batis diops"},{"birdId":"norpuf1","commonName":"Northern Puffback","sciName":"Dryoscopus gambensis"},{"birdId":"wtcfly1","commonName":"White-tailed Crested Flycatcher","sciName":"Elminia albonotata"},{"birdId":"stbtit2","commonName":"Stripe-breasted Tit","sciName":"Melaniparus fasciiventer"},{"birdId":"banpri1","commonName":"Banded Prinia","sciName":"Prinia bairdii"},{"birdId":"cibwar1","commonName":"Cinnamon Bracken-Warbler","sciName":"Bradypterus cinnamomeus"},{"birdId":"yewgre1","commonName":"Yellow-whiskered Greenbul","sciName":"Eurillas latirostris"},{"birdId":"yesbul1","commonName":"Yellow-streaked Greenbul","sciName":"Phyllastrephus flavostriatus"},{"birdId":"rfwwar1","commonName":"Red-faced Woodland-Warbler","sciName":"Phylloscopus laetus"},{"birdId":"retale1","commonName":"Red-throated Alethe","sciName":"Chamaetylas poliophrys"},{"birdId":"colsun2","commonName":"Collared Sunbird","sciName":"Hedydipna collaris"},{"birdId":"buhsun1","commonName":"Blue-headed Sunbird","sciName":"Cyanomitra alinae"},{"birdId":"pubsun3","commonName":"Purple-breasted Sunbird","sciName":"Nectarinia purpureiventris"},{"birdId":"stusun1","commonName":"Stuhlmann's Sunbird","sciName":"Cinnyris stuhlmanni"},{"birdId":"strwea1","commonName":"Strange Weaver","sciName":"Ploceus alienus"},{"birdId":"kanwax1","commonName":"Kandt's Waxbill","sciName":"Estrilda kandti"},{"birdId":"comwax","commonName":"Common Waxbill","sciName":"Estrilda astrild"},{"birdId":"combuz1","commonName":"Common Buzzard","sciName":"Buteo buteo"},{"birdId":"whhwoo1","commonName":"White-headed Woodhoopoe","sciName":"Phoeniculus bollei"},{"birdId":"yeccan1","commonName":"Yellow-crowned Canary","sciName":"Serinus flavivertex"},{"birdId":"tamdov1","commonName":"Tambourine Dove","sciName":"Turtur tympanistria"},{"birdId":"neuwar1","commonName":"Neumann's Warbler","sciName":"Hemitesia neumanni"},{"birdId":"ruwapa1","commonName":"Rwenzori Apalis","sciName":"Oreolais ruwenzorii"},{"birdId":"chtapa3","commonName":"Chestnut-throated Apalis","sciName":"Apalis porphyrolaema"},{"birdId":"abgthr1","commonName":"Abyssinian Ground-Thrush","sciName":"Geokichla piaggiae"},{"birdId":"afywhe2","commonName":"Northern Yellow White-eye","sciName":"Zosterops senegalensis"},{"birdId":"whbcro2","commonName":"White-browed Crombec","sciName":"Sylvietta leucophrys"},{"birdId":"moubuz2","commonName":"Mountain Buzzard","sciName":"Buteo oreophilus"},{"birdId":"mosbou4","commonName":"Albertine Boubou","sciName":"Laniarius holomelas"},{"birdId":"whnrav1","commonName":"White-necked Raven","sciName":"Corvus albicollis"},{"birdId":"gryapa1","commonName":"Gray Apalis","sciName":"Apalis cinerea"},{"birdId":"bltori1","commonName":"Black-tailed Oriole","sciName":"Oriolus percivali"},{"birdId":"bltapa1","commonName":"Black-throated Apalis","sciName":"Apalis jacksoni"},{"birdId":"mouill1","commonName":"Mountain Illadopsis","sciName":"Illadopsis pyrrhoptera"},{"birdId":"bltcuc1","commonName":"Barred Long-tailed Cuckoo","sciName":"Cercococcyx montanus"},{"birdId":"bkfruw1","commonName":"Black-faced Rufous-Warbler","sciName":"Bathmocercus rufus"},{"birdId":"grbtur1","commonName":"Great Blue Turaco","sciName":"Corythaeola cristata"},{"birdId":"arrcha1","commonName":"Archer's Robin-Chat","sciName":"Cossypha archeri"},{"birdId":"dohbus1","commonName":"Doherty's Bushshrike","sciName":"Telophorus dohertyi"},{"birdId":"easmog1","commonName":"Eastern Mountain Greenbul","sciName":"Arizelocichla nigriceps"},{"birdId":"rekcoo1","commonName":"Red-knobbed Coot","sciName":"Fulica cristata"},{"birdId":"hadibi1","commonName":"Hadada Ibis","sciName":"Bostrychia hagedash"},{"birdId":"malsun1","commonName":"Malachite Sunbird","sciName":"Nectarinia famosa"},{"birdId":"leahon2","commonName":"Least Honeyguide","sciName":"Indicator exilis"},{"birdId":"abhori1","commonName":"African Black-headed Oriole","sciName":"Oriolus larvatus"},{"birdId":"chibat1","commonName":"Chinspot Batis","sciName":"Batis molitor"},{"birdId":"afpfly1","commonName":"African Paradise-Flycatcher","sciName":"Terpsiphone viridis"},{"birdId":"wtbfly1","commonName":"White-tailed Blue Flycatcher","sciName":"Elminia albicauda"},{"birdId":"whcpri2","commonName":"White-chinned Prinia","sciName":"Schistolais leucopogon"},{"birdId":"moywar1","commonName":"Mountain Yellow-Warbler","sciName":"Iduna similis"},{"birdId":"slbgre1","commonName":"Slender-billed Greenbul","sciName":"Stelgidillas gracilirostris"},{"birdId":"afhbab3","commonName":"Rwenzori Hill Babbler","sciName":"Sylvia atriceps"},{"birdId":"broill1","commonName":"Brown Illadopsis","sciName":"Illadopsis fulvescens"},{"birdId":"yebfly2","commonName":"Yellow-eyed Black-Flycatcher","sciName":"Melaenornis ardesiacus"},{"birdId":"whsrob1","commonName":"White-starred Robin","sciName":"Pogonocichla stellata"},{"birdId":"equaka1","commonName":"Equatorial Akalat","sciName":"Sheppardia aequatorialis"},{"birdId":"ducwin1","commonName":"Dusky Crimsonwing","sciName":"Cryptospiza jacksoni"},{"birdId":"blcwax2","commonName":"Black-crowned Waxbill","sciName":"Estrilda nonnula"},{"birdId":"bkskit1","commonName":"Black-winged Kite","sciName":"Elanus caeruleus"},{"birdId":"afhhaw1","commonName":"African Harrier-Hawk","sciName":"Polyboroides typus"},{"birdId":"crheag1","commonName":"Crowned Eagle","sciName":"Stephanoaetus coronatus"},{"birdId":"loceag1","commonName":"Long-crested Eagle","sciName":"Lophaetus occipitalis"},{"birdId":"brctch1","commonName":"Brown-crowned Tchagra","sciName":"Tchagra australis"},{"birdId":"eaosun1","commonName":"Olive Sunbird","sciName":"Cyanomitra olivacea"},{"birdId":"varsun2","commonName":"Variable Sunbird","sciName":"Cinnyris venustus"},{"birdId":"afrgrp1","commonName":"African Green-Pigeon","sciName":"Treron calvus"},{"birdId":"reccuc1","commonName":"Red-chested Cuckoo","sciName":"Cuculus solitarius"},{"birdId":"grycus1","commonName":"Gray Cuckooshrike","sciName":"Coracina caesia"},{"birdId":"blbpuf2","commonName":"Black-backed Puffback","sciName":"Dryoscopus cubla"},{"birdId":"shegre1","commonName":"Shelley's Greenbul","sciName":"Arizelocichla masukuensis"},{"birdId":"slbsta1","commonName":"Slender-billed Starling","sciName":"Onychognathus tenuirostris"},{"birdId":"stusta1","commonName":"Stuhlmann's Starling","sciName":"Poeoptera stuhlmanni"},{"birdId":"abythr1","commonName":"Abyssinian Thrush","sciName":"Turdus abyssinicus"},{"birdId":"ashfly1","commonName":"Ashy Flycatcher","sciName":"Fraseria caerulescens"},{"birdId":"whcoli1","commonName":"White-collared Oliveback","sciName":"Nesocharis ansorgei"},{"birdId":"rehblu1","commonName":"Red-headed Bluebill","sciName":"Spermophaga ruficapilla"},{"birdId":"mouwag1","commonName":"Mountain Wagtail","sciName":"Motacilla clara"},{"birdId":"grywag","commonName":"Gray Wagtail","sciName":"Motacilla cinerea"},{"birdId":"yebduc1","commonName":"Yellow-billed Duck","sciName":"Anas undulata"},{"birdId":"shasta2","commonName":"Sharpe's Starling","sciName":"Pholia sharpii"}]