[{"birdId":"comchi1","commonName":"Common Chiffchaff","sciName":"Phylloscopus collybita"},{"birdId":"blared1","commonName":"Black Redstart","sciName":"Phoenicurus ochruros"},{"birdId":"yelgul1","commonName":"Yellow-legged Gull","sciName":"Larus michahellis"},{"birdId":"armgul1","commonName":"Armenian Gull","sciName":"Larus armenicus"},{"birdId":"lbbgul","commonName":"Lesser Black-backed Gull","sciName":"Larus fuscus"},{"birdId":"gubter2","commonName":"Gull-billed Tern","sciName":"Gelochelidon nilotica"},{"birdId":"whiter2","commonName":"Whiskered Tern","sciName":"Chlidonias hybrida"},{"birdId":"whwter","commonName":"White-winged Tern","sciName":"Chlidonias leucopterus"},{"birdId":"santer1","commonName":"Sandwich Tern","sciName":"Thalasseus sandvicensis"},{"birdId":"parjae","commonName":"Parasitic Jaeger","sciName":"Stercorarius parasiticus"},{"birdId":"corbun1","commonName":"Corn Bunting","sciName":"Emberiza calandra"},{"birdId":"gargan","commonName":"Garganey","sciName":"Spatula querquedula"},{"birdId":"gnwtea","commonName":"Green-winged Teal","sciName":"Anas crecca"},{"birdId":"comqua1","commonName":"Common Quail","sciName":"Coturnix coturnix"},{"birdId":"eucdov","commonName":"Eurasian Collared-Dove","sciName":"Streptopelia decaocto"},{"birdId":"laudov1","commonName":"Laughing Dove","sciName":"Spilopelia senegalensis"},{"birdId":"eurnig1","commonName":"Eurasian Nightjar","sciName":"Caprimulgus europaeus"},{"birdId":"corplo","commonName":"Common Ringed Plover","sciName":"Charadrius hiaticula"},{"birdId":"spwlap1","commonName":"Spur-winged Lapwing","sciName":"Vanellus spinosus"},{"birdId":"kenplo1","commonName":"Kentish Plover","sciName":"Anarhynchus alexandrinus"},{"birdId":"whimbr","commonName":"Whimbrel","sciName":"Numenius phaeopus"},{"birdId":"eurcur","commonName":"Eurasian Curlew","sciName":"Numenius arquata"},{"birdId":"comsan","commonName":"Common Sandpiper","sciName":"Actitis hypoleucos"},{"birdId":"comred1","commonName":"Common Redshank","sciName":"Tringa totanus"},{"birdId":"spored","commonName":"Spotted Redshank","sciName":"Tringa erythropus"},{"birdId":"ruff","commonName":"Ruff","sciName":"Calidris pugnax"},{"birdId":"sander","commonName":"Sanderling","sciName":"Calidris alba"},{"birdId":"dunlin","commonName":"Dunlin","sciName":"Calidris alpina"},{"birdId":"litsti","commonName":"Little Stint","sciName":"Calidris minuta"},{"birdId":"litter1","commonName":"Little Tern","sciName":"Sternula albifrons"},{"birdId":"comter","commonName":"Common Tern","sciName":"Sterna hirundo"},{"birdId":"bcnher","commonName":"Black-crowned Night Heron","sciName":"Nycticorax nycticorax"},{"birdId":"litegr","commonName":"Little Egret","sciName":"Egretta garzetta"},{"birdId":"wemhar1","commonName":"Western Marsh Harrier","sciName":"Circus aeruginosus"},{"birdId":"hoopoe","commonName":"Eurasian Hoopoe","sciName":"Upupa epops"},{"birdId":"comkin1","commonName":"Common Kingfisher","sciName":"Alcedo atthis"},{"birdId":"eurkes","commonName":"Eurasian Kestrel","sciName":"Falco tinnunculus"},{"birdId":"masshr1","commonName":"Masked Shrike","sciName":"Lanius nubicus"},{"birdId":"hoocro1","commonName":"Hooded Crow","sciName":"Corvus cornix"},{"birdId":"gstlar1","commonName":"Greater Short-toed Lark","sciName":"Calandrella brachydactyla"},{"birdId":"crelar1","commonName":"Crested Lark","sciName":"Galerida cristata"},{"birdId":"grapri1","commonName":"Graceful Prinia","sciName":"Prinia gracilis"},{"birdId":"banswa","commonName":"Bank Swallow","sciName":"Riparia riparia"},{"birdId":"barswa","commonName":"Barn Swallow","sciName":"Hirundo rustica"},{"birdId":"leswhi4","commonName":"Lesser Whitethroat","sciName":"Curruca curruca"},{"birdId":"comred2","commonName":"Common Redstart","sciName":"Phoenicurus phoenicurus"},{"birdId":"norwhe","commonName":"Northern Wheatear","sciName":"Oenanthe oenanthe"},{"birdId":"isawhe1","commonName":"Isabelline Wheatear","sciName":"Oenanthe isabellina"},{"birdId":"houspa","commonName":"House Sparrow","sciName":"Passer domesticus"},{"birdId":"eaywag1","commonName":"Western Yellow Wagtail","sciName":"Motacilla flava"},{"birdId":"whiwag","commonName":"White Wagtail","sciName":"Motacilla alba"},{"birdId":"commyn","commonName":"Common Myna","sciName":"Acridotheres tristis"},{"birdId":"commoo3","commonName":"Eurasian Moorhen","sciName":"Gallinula chloropus"},{"birdId":"bkhgul","commonName":"Black-headed Gull","sciName":"Chroicocephalus ridibundus"},{"birdId":"piekin1","commonName":"Pied Kingfisher","sciName":"Ceryle rudis"},{"birdId":"mallar3","commonName":"Mallard","sciName":"Anas platyrhynchos"},{"birdId":"eurspo1","commonName":"Eurasian Spoonbill","sciName":"Platalea leucorodia"},{"birdId":"bkskit1","commonName":"Black-winged Kite","sciName":"Elanus caeruleus"},{"birdId":"egyvul1","commonName":"Egyptian Vulture","sciName":"Neophron percnopterus"},{"birdId":"whtwhe1","commonName":"White-crowned Wheatear","sciName":"Oenanthe leucopyga"}]