[{"birdId":"incdov","commonName":"Inca Dove","sciName":"Columbina inca"},{"birdId":"whwdov","commonName":"White-winged Dove","sciName":"Zenaida asiatica"},{"birdId":"willet1","commonName":"Willet","sciName":"Tringa semipalmata"},{"birdId":"brnpel","commonName":"Brown Pelican","sciName":"Pelecanus occidentalis"},{"birdId":"triher","commonName":"Tricolored Heron","sciName":"Egretta tricolor"},{"birdId":"categr1","commonName":"Western Cattle Egret","sciName":"Bubulcus ibis"},{"birdId":"orcpar","commonName":"Orange-chinned Parakeet","sciName":"Brotogeris jugularis"},{"birdId":"grekis","commonName":"Great Kiskadee","sciName":"Pitangus sulphuratus"},{"birdId":"trokin","commonName":"Tropical Kingbird","sciName":"Tyrannus melancholicus"},{"birdId":"gybmar","commonName":"Gray-breasted Martin","sciName":"Progne chalybea"},{"birdId":"runwre1","commonName":"Rufous-naped Wren","sciName":"Campylorhynchus rufinucha"},{"birdId":"clcrob","commonName":"Clay-colored Thrush","sciName":"Turdus grayi"},{"birdId":"stbori","commonName":"Streak-backed Oriole","sciName":"Icterus pustulatus"},{"birdId":"melbla1","commonName":"Melodious Blackbird","sciName":"Dives dives"},{"birdId":"grtgra","commonName":"Great-tailed Grackle","sciName":"Quiscalus mexicanus"},{"birdId":"grasal2","commonName":"Cinnamon-bellied Saltator","sciName":"Saltator grandis"},{"birdId":"caneme1","commonName":"Canivet's Emerald","sciName":"Cynanthus canivetii"},{"birdId":"royter1","commonName":"Royal Tern","sciName":"Thalasseus maximus"},{"birdId":"magfri","commonName":"Magnificent Frigatebird","sciName":"Fregata magnificens"},{"birdId":"blkvul","commonName":"Black Vulture","sciName":"Coragyps atratus"},{"birdId":"gofwoo","commonName":"Golden-fronted Woodpecker","sciName":"Melanerpes aurifrons"},{"birdId":"crebob1","commonName":"Crested Bobwhite","sciName":"Colinus cristatus"},{"birdId":"grbani","commonName":"Groove-billed Ani","sciName":"Crotophaga sulcirostris"},{"birdId":"strcuc1","commonName":"Striped Cuckoo","sciName":"Tapera naevia"},{"birdId":"gryhaw2","commonName":"Gray Hawk","sciName":"Buteo plagiatus"},{"birdId":"sthspa1","commonName":"Stripe-headed Sparrow","sciName":"Peucaea ruficauda"},{"birdId":"rugdov","commonName":"Ruddy Ground Dove","sciName":"Columbina talpacoti"},{"birdId":"turvul","commonName":"Turkey Vulture","sciName":"Cathartes aura"},{"birdId":"socfly1","commonName":"Social Flycatcher","sciName":"Myiozetetes similis"},{"birdId":"subfly","commonName":"Sulphur-bellied Flycatcher","sciName":"Myiodynastes luteiventris"},{"birdId":"bugtan","commonName":"Blue-gray Tanager","sciName":"Thraupis episcopus"},{"birdId":"orfpar","commonName":"Orange-fronted Parakeet","sciName":"Eupsittula canicularis"},{"birdId":"houspa","commonName":"House Sparrow","sciName":"Passer domesticus"},{"birdId":"rocpig","commonName":"Rock Pigeon","sciName":"Columba livia"},{"birdId":"pacpar1","commonName":"Pacific Parakeet","sciName":"Psittacara strenuus"},{"birdId":"rebpig1","commonName":"Red-billed Pigeon","sciName":"Patagioenas flavirostris"},{"birdId":"cogdov","commonName":"Common Ground Dove","sciName":"Columbina passerina"},{"birdId":"cinhum1","commonName":"Cinnamon Hummingbird","sciName":"Amazilia rutila"},{"birdId":"manrai1","commonName":"Mangrove Rail","sciName":"Rallus longirostris"},{"birdId":"bknsti","commonName":"Black-necked Stilt","sciName":"Himantopus mexicanus"},{"birdId":"neocor","commonName":"Neotropic Cormorant","sciName":"Nannopterum brasilianum"},{"birdId":"libher","commonName":"Little Blue Heron","sciName":"Egretta caerulea"},{"birdId":"greegr","commonName":"Great Egret","sciName":"Ardea alba"},{"birdId":"grbher3","commonName":"Great Blue Heron","sciName":"Ardea herodias"},{"birdId":"whiibi","commonName":"White Ibis","sciName":"Eudocimus albus"},{"birdId":"comblh1","commonName":"Common Black Hawk","sciName":"Buteogallus anthracinus"},{"birdId":"tubmot1","commonName":"Turquoise-browed Motmot","sciName":"Eumomota superciliosa"},{"birdId":"ducfly","commonName":"Dusky-capped Flycatcher","sciName":"Myiarchus tuberculifer"},{"birdId":"rubpep1","commonName":"Rufous-browed Peppershrike","sciName":"Cyclarhis gujanensis"},{"birdId":"wtmjay1","commonName":"White-throated Magpie-Jay","sciName":"Calocitta formosa"},{"birdId":"manswa1","commonName":"Mangrove Swallow","sciName":"Tachycineta albilinea"},{"birdId":"yelwar","commonName":"Yellow Warbler","sciName":"Setophaga petechia"},{"birdId":"rubsee1","commonName":"Ruddy-breasted Seedeater","sciName":"Sporophila minuta"},{"birdId":"ameoys","commonName":"American Oystercatcher","sciName":"Haematopus palliatus"},{"birdId":"bkbplo","commonName":"Black-bellied Plover","sciName":"Pluvialis squatarola"},{"birdId":"semplo","commonName":"Semipalmated Plover","sciName":"Charadrius semipalmatus"},{"birdId":"wilplo","commonName":"Wilson's Plover","sciName":"Anarhynchus wilsonia"},{"birdId":"whimbr","commonName":"Whimbrel","sciName":"Numenius phaeopus"},{"birdId":"margod","commonName":"Marbled Godwit","sciName":"Limosa fedoa"},{"birdId":"rudtur","commonName":"Ruddy Turnstone","sciName":"Arenaria interpres"},{"birdId":"laugul","commonName":"Laughing Gull","sciName":"Leucophaeus atricilla"},{"birdId":"fragul","commonName":"Franklin's Gull","sciName":"Leucophaeus pipixcan"},{"birdId":"calgul","commonName":"California Gull","sciName":"Larus californicus"},{"birdId":"blkski","commonName":"Black Skimmer","sciName":"Rynchops niger"},{"birdId":"leater1","commonName":"Least Tern","sciName":"Sternula antillarum"},{"birdId":"comter","commonName":"Common Tern","sciName":"Sterna hirundo"},{"birdId":"santer1","commonName":"Sandwich Tern","sciName":"Thalasseus sandvicensis"},{"birdId":"eleter1","commonName":"Elegant Tern","sciName":"Thalasseus elegans"},{"birdId":"amwpel","commonName":"American White Pelican","sciName":"Pelecanus erythrorhynchos"},{"birdId":"roahaw","commonName":"Roadside Hawk","sciName":"Rupornis magnirostris"},{"birdId":"blhtro1","commonName":"Black-headed Trogon","sciName":"Trogon melanocephalus"},{"birdId":"cotfly1","commonName":"Common Tody-Flycatcher","sciName":"Todirostrum cinereum"},{"birdId":"yebela1","commonName":"Yellow-bellied Elaenia","sciName":"Elaenia flavogaster"},{"birdId":"nutfly","commonName":"Nutting's Flycatcher","sciName":"Myiarchus nuttingi"},{"birdId":"tromoc","commonName":"Tropical Mockingbird","sciName":"Mimus gilvus"},{"birdId":"whcsee1","commonName":"Morelet's Seedeater","sciName":"Sporophila morelleti"},{"birdId":"eucdov","commonName":"Eurasian Collared-Dove","sciName":"Streptopelia decaocto"},{"birdId":"grnher","commonName":"Green Heron","sciName":"Butorides virescens"},{"birdId":"nrwswa","commonName":"Northern Rough-winged Swallow","sciName":"Stelgidopteryx serripennis"},{"birdId":"hudgod","commonName":"Hudsonian Godwit","sciName":"Limosa haemastica"},{"birdId":"sposan","commonName":"Spotted Sandpiper","sciName":"Actitis macularius"},{"birdId":"snoegr","commonName":"Snowy Egret","sciName":"Egretta thula"},{"birdId":"bncfly","commonName":"Brown-crested Flycatcher","sciName":"Myiarchus tyrannulus"},{"birdId":"whbcha1","commonName":"White-bellied Chachalaca","sciName":"Ortalis leucogastra"},{"birdId":"leasan","commonName":"Least Sandpiper","sciName":"Calidris minutilla"},{"birdId":"rosspo1","commonName":"Roseate Spoonbill","sciName":"Platalea ajaja"},{"birdId":"fepowl","commonName":"Ferruginous Pygmy-Owl","sciName":"Glaucidium brasilianum"},{"birdId":"whlgna2","commonName":"White-lored Gnatcatcher","sciName":"Polioptila albiloris"},{"birdId":"banwre1","commonName":"Banded Wren","sciName":"Thryophilus pleurostictus"},{"birdId":"spbori","commonName":"Spot-breasted Oriole","sciName":"Icterus pectoralis"},{"birdId":"altori","commonName":"Altamira Oriole","sciName":"Icterus gularis"},{"birdId":"labwoo","commonName":"Ladder-backed Woodpecker","sciName":"Dryobates scalaris"},{"birdId":"sthwoo1","commonName":"Streak-headed Woodcreeper","sciName":"Lepidocolaptes souleyetii"},{"birdId":"rotbec","commonName":"Rose-throated Becard","sciName":"Pachyramphus aglaiae"},{"birdId":"manvir1","commonName":"Mangrove Vireo","sciName":"Vireo pallens"},{"birdId":"redegr","commonName":"Reddish Egret","sciName":"Egretta rufescens"},{"birdId":"dstkne","commonName":"Double-striped Thick-knee","sciName":"Hesperoburhinus bistriatus"},{"birdId":"easmea","commonName":"Eastern Meadowlark","sciName":"Sturnella magna"},{"birdId":"musduc","commonName":"Muscovy Duck","sciName":"Cairina moschata"},{"birdId":"yegvir","commonName":"Yellow-green Vireo","sciName":"Vireo flavoviridis"},{"birdId":"whtdov","commonName":"White-tipped Dove","sciName":"Leptotila verreauxi"},{"birdId":"colplo1","commonName":"Collared Plover","sciName":"Anarhynchus collaris"},{"birdId":"bobfly1","commonName":"Boat-billed Flycatcher","sciName":"Megarynchus pitangua"},{"birdId":"easkin","commonName":"Eastern Kingbird","sciName":"Tyrannus tyrannus"},{"birdId":"rawwre1","commonName":"Rufous-and-white Wren","sciName":"Thryophilus rufalbus"},{"birdId":"wantat1","commonName":"Wandering Tattler","sciName":"Tringa incana"},{"birdId":"surfbi","commonName":"Surfbird","sciName":"Calidris virgata"},{"birdId":"lesnig","commonName":"Lesser Nighthawk","sciName":"Chordeiles acutipennis"},{"birdId":"sander","commonName":"Sanderling","sciName":"Calidris alba"},{"birdId":"ycnher","commonName":"Yellow-crowned Night Heron","sciName":"Nyctanassa violacea"},{"birdId":"barswa","commonName":"Barn Swallow","sciName":"Hirundo rustica"},{"birdId":"norwat","commonName":"Northern Waterthrush","sciName":"Parkesia noveboracensis"},{"birdId":"moudov","commonName":"Mourning Dove","sciName":"Zenaida macroura"},{"birdId":"grnkin","commonName":"Green Kingfisher","sciName":"Chloroceryle americana"},{"birdId":"balori","commonName":"Baltimore Oriole","sciName":"Icterus galbula"},{"birdId":"blhsal1","commonName":"Black-headed Saltator","sciName":"Saltator atriceps"},{"birdId":"tropew4","commonName":"Northern Tropical Pewee","sciName":"Contopus bogotensis"},{"birdId":"plawre1","commonName":"Cabanis's Wren","sciName":"Cantorchilus modestus"},{"birdId":"lesgol","commonName":"Lesser Goldfinch","sciName":"Spinus psaltria"},{"birdId":"wessan","commonName":"Western Sandpiper","sciName":"Calidris mauri"},{"birdId":"banswa","commonName":"Bank Swallow","sciName":"Riparia riparia"},{"birdId":"bawwar","commonName":"Black-and-white Warbler","sciName":"Mniotilta varia"},{"birdId":"tenwar","commonName":"Tennessee Warbler","sciName":"Leiothlypis peregrina"},{"birdId":"mancuc","commonName":"Mangrove Cuckoo","sciName":"Coccyzus minor"},{"birdId":"ivbwoo1","commonName":"Ivory-billed Woodcreeper","sciName":"Xiphorhynchus flavigaster"},{"birdId":"screup1","commonName":"Scrub Euphonia","sciName":"Euphonia affinis"},{"birdId":"amered","commonName":"American Redstart","sciName":"Setophaga ruticilla"},{"birdId":"shbdow","commonName":"Short-billed Dowitcher","sciName":"Limnodromus griseus"},{"birdId":"sctfly","commonName":"Scissor-tailed Flycatcher","sciName":"Tyrannus forficatus"},{"birdId":"squcuc1","commonName":"Squirrel Cuckoo","sciName":"Piaya cayana"},{"birdId":"bucmot2","commonName":"Lesson's Motmot","sciName":"Momotus lessonii"},{"birdId":"grcfly","commonName":"Great Crested Flycatcher","sciName":"Myiarchus crinitus"},{"birdId":"fatwar","commonName":"Fan-tailed Warbler","sciName":"Basileuterus lachrymosus"},{"birdId":"westan","commonName":"Western Tanager","sciName":"Piranga ludoviciana"},{"birdId":"gubter2","commonName":"Gull-billed Tern","sciName":"Gelochelidon nilotica"},{"birdId":"caster1","commonName":"Caspian Tern","sciName":"Hydroprogne caspia"},{"birdId":"sumtan","commonName":"Summer Tanager","sciName":"Piranga rubra"},{"birdId":"mastit1","commonName":"Masked Tityra","sciName":"Tityra semifasciata"},{"birdId":"legcuc1","commonName":"Lesser Ground-Cuckoo","sciName":"Morococcyx erythropygus"},{"birdId":"vauswi","commonName":"Vaux's Swift","sciName":"Chaetura vauxi"},{"birdId":"yebsap","commonName":"Yellow-bellied Sapsucker","sciName":"Sphyrapicus varius"},{"birdId":"linwoo1","commonName":"Lineated Woodpecker","sciName":"Dryocopus lineatus"},{"birdId":"barant1","commonName":"Barred Antshrike","sciName":"Thamnophilus doliatus"},{"birdId":"yebfly","commonName":"Yellow-bellied Flycatcher","sciName":"Empidonax flaviventris"},{"birdId":"weskin","commonName":"Western Kingbird","sciName":"Tyrannus verticalis"},{"birdId":"paibun","commonName":"Painted Bunting","sciName":"Passerina ciris"},{"birdId":"lesyel","commonName":"Lesser Yellowlegs","sciName":"Tringa flavipes"},{"birdId":"stisan","commonName":"Stilt Sandpiper","sciName":"Calidris himantopus"},{"birdId":"killde","commonName":"Killdeer","sciName":"Charadrius vociferus"},{"birdId":"greyel","commonName":"Greater Yellowlegs","sciName":"Tringa melanoleuca"},{"birdId":"osprey","commonName":"Osprey","sciName":"Pandion haliaetus"},{"birdId":"woosto","commonName":"Wood Stork","sciName":"Mycteria americana"},{"birdId":"lobdow","commonName":"Long-billed Dowitcher","sciName":"Limnodromus scolopaceus"},{"birdId":"redkno","commonName":"Red Knot","sciName":"Calidris canutus"},{"birdId":"semsan","commonName":"Semipalmated Sandpiper","sciName":"Calidris pusilla"},{"birdId":"lobcur","commonName":"Long-billed Curlew","sciName":"Numenius americanus"},{"birdId":"anhing","commonName":"Anhinga","sciName":"Anhinga anhinga"},{"birdId":"perfal","commonName":"Peregrine Falcon","sciName":"Falco peregrinus"},{"birdId":"rthhum","commonName":"Ruby-throated Hummingbird","sciName":"Archilochus colubris"},{"birdId":"orcori","commonName":"Orchard Oriole","sciName":"Icterus spurius"},{"birdId":"shthaw","commonName":"Short-tailed Hawk","sciName":"Buteo brachyurus"},{"birdId":"verfly","commonName":"Vermilion Flycatcher","sciName":"Pyrocephalus rubinus"},{"birdId":"graspa","commonName":"Grasshopper Sparrow","sciName":"Ammodramus savannarum"},{"birdId":"larspa","commonName":"Lark Sparrow","sciName":"Chondestes grammacus"},{"birdId":"brocow","commonName":"Bronzed Cowbird","sciName":"Molothrus aeneus"},{"birdId":"bbwduc","commonName":"Black-bellied Whistling-Duck","sciName":"Dendrocygna autumnalis"},{"birdId":"fuwduc","commonName":"Fulvous Whistling-Duck","sciName":"Dendrocygna bicolor"},{"birdId":"buwtea","commonName":"Blue-winged Teal","sciName":"Spatula discors"},{"birdId":"leagre","commonName":"Least Grebe","sciName":"Tachybaptus dominicus"},{"birdId":"comgal1","commonName":"Common Gallinule","sciName":"Gallinula galeata"},{"birdId":"y00475","commonName":"American Coot","sciName":"Fulica americana"},{"birdId":"limpki","commonName":"Limpkin","sciName":"Aramus guarauna"},{"birdId":"norjac","commonName":"Northern Jacana","sciName":"Jacana spinosa"},{"birdId":"zothaw","commonName":"Zone-tailed Hawk","sciName":"Buteo albonotatus"},{"birdId":"snakit","commonName":"Snail Kite","sciName":"Rostrhamus sociabilis"},{"birdId":"rinkin1","commonName":"Ringed Kingfisher","sciName":"Megaceryle torquata"},{"birdId":"peakit1","commonName":"Pearl Kite","sciName":"Gampsonyx swainsonii"},{"birdId":"brnboo","commonName":"Brown Booby","sciName":"Sula leucogaster"},{"birdId":"colara1","commonName":"Collared Aracari","sciName":"Pteroglossus torquatus"},{"birdId":"yetvir","commonName":"Yellow-throated Vireo","sciName":"Vireo flavifrons"},{"birdId":"wlswar","commonName":"Wilson's Warbler","sciName":"Cardellina pusilla"},{"birdId":"grhowl","commonName":"Great Horned Owl","sciName":"Bubo virginianus"},{"birdId":"coffal1","commonName":"Collared Forest-Falcon","sciName":"Micrastur semitorquatus"},{"birdId":"eawpew","commonName":"Eastern Wood-Pewee","sciName":"Contopus virens"},{"birdId":"hobkit","commonName":"Hook-billed Kite","sciName":"Chondrohierax uncinatus"},{"birdId":"bkbwar","commonName":"Blackburnian Warbler","sciName":"Setophaga fusca"},{"birdId":"dickci","commonName":"Dickcissel","sciName":"Spiza americana"},{"birdId":"brwhaw","commonName":"Broad-winged Hawk","sciName":"Buteo platypterus"},{"birdId":"swahaw","commonName":"Swainson's Hawk","sciName":"Buteo swainsoni"},{"birdId":"coohaw","commonName":"Cooper's Hawk","sciName":"Accipiter cooperii"},{"birdId":"norsho","commonName":"Northern Shoveler","sciName":"Spatula clypeata"},{"birdId":"gnbman","commonName":"Green-breasted Mango","sciName":"Anthracothorax prevostii"},{"birdId":"pecsan","commonName":"Pectoral Sandpiper","sciName":"Calidris melanotos"},{"birdId":"blkpho","commonName":"Black Phoebe","sciName":"Sayornis nigricans"},{"birdId":"rewbla","commonName":"Red-winged Blackbird","sciName":"Agelaius phoeniceus"},{"birdId":"btther1","commonName":"Bare-throated Tiger-Heron","sciName":"Tigrisoma mexicanum"},{"birdId":"y00678","commonName":"Crested Caracara","sciName":"Caracara plancus"},{"birdId":"eletro","commonName":"Elegant Trogon","sciName":"Trogon elegans"},{"birdId":"grnpar","commonName":"Green Parakeet","sciName":"Psittacara holochlorus"},{"birdId":"yebori1","commonName":"Yellow-backed Oriole","sciName":"Icterus chrysater"},{"birdId":"plukit1","commonName":"Plumbeous Kite","sciName":"Ictinia plumbea"},{"birdId":"yewtan1","commonName":"Yellow-winged Tanager","sciName":"Thraupis abbas"},{"birdId":"rucwar4","commonName":"Chestnut-capped Warbler","sciName":"Basileuterus delattrii"},{"birdId":"goowoo1","commonName":"Golden-olive Woodpecker","sciName":"Colaptes rubiginosus"},{"birdId":"yebcac1","commonName":"Yellow-billed Cacique","sciName":"Amblycercus holosericeus"},{"birdId":"yeofly1","commonName":"Yellow-olive Flatbill","sciName":"Tolmomyias sulphurescens"},{"birdId":"wilpha","commonName":"Wilson's Phalarope","sciName":"Phalaropus tricolor"},{"birdId":"laufal1","commonName":"Laughing Falcon","sciName":"Herpetotheres cachinnans"},{"birdId":"soulap1","commonName":"Southern Lapwing","sciName":"Vanellus chilensis"},{"birdId":"chswar","commonName":"Chestnut-sided Warbler","sciName":"Setophaga pensylvanica"},{"birdId":"blbgra1","commonName":"Blue-black Grassquit","sciName":"Volatinia jacarina"},{"birdId":"compau","commonName":"Common Pauraque","sciName":"Nyctidromus albicollis"},{"birdId":"uplsan","commonName":"Upland Sandpiper","sciName":"Bartramia longicauda"},{"birdId":"plcsta","commonName":"Plain-capped Starthroat","sciName":"Heliomaster constantii"},{"birdId":"wilfly","commonName":"Willow Flycatcher","sciName":"Empidonax traillii"},{"birdId":"robgro","commonName":"Rose-breasted Grosbeak","sciName":"Pheucticus ludovicianus"},{"birdId":"amakin1","commonName":"Amazon Kingfisher","sciName":"Chloroceryle amazona"},{"birdId":"houwre","commonName":"House Wren","sciName":"Troglodytes aedon"},{"birdId":"berhum","commonName":"Berylline Hummingbird","sciName":"Saucerottia beryllina"},{"birdId":"indbun","commonName":"Indigo Bunting","sciName":"Passerina cyanea"},{"birdId":"phecuc1","commonName":"Pheasant Cuckoo","sciName":"Dromococcyx phasianellus"},{"birdId":"merlin","commonName":"Merlin","sciName":"Falco columbarius"},{"birdId":"nobtyr","commonName":"Northern Beardless-Tyrannulet","sciName":"Camptostoma imberbe"},{"birdId":"blugrb1","commonName":"Blue Grosbeak","sciName":"Passerina caerulea"},{"birdId":"purgal2","commonName":"Purple Gallinule","sciName":"Porphyrio martinica"},{"birdId":"buhvir","commonName":"Blue-headed Vireo","sciName":"Vireo solitarius"},{"birdId":"magwar","commonName":"Magnolia Warbler","sciName":"Setophaga magnolia"},{"birdId":"warvir","commonName":"Warbling Vireo","sciName":"Vireo gilvus"},{"birdId":"gartro1","commonName":"Gartered Trogon","sciName":"Trogon caligatus"},{"birdId":"relhon1","commonName":"Red-legged Honeycreeper","sciName":"Cyanerpes cyaneus"},{"birdId":"amekes","commonName":"American Kestrel","sciName":"Falco sparverius"},{"birdId":"whcswi","commonName":"White-collared Swift","sciName":"Streptoprocne zonaris"},{"birdId":"leafly","commonName":"Least Flycatcher","sciName":"Empidonax minimus"},{"birdId":"lesgre1","commonName":"Lesser Greenlet","sciName":"Pachysylvia decurtata"},{"birdId":"ovenbi1","commonName":"Ovenbird","sciName":"Seiurus aurocapilla"},{"birdId":"yerwar","commonName":"Yellow-rumped Warbler","sciName":"Setophaga coronata"},{"birdId":"miskit","commonName":"Mississippi Kite","sciName":"Ictinia mississippiensis"},{"birdId":"ameavo","commonName":"American Avocet","sciName":"Recurvirostra americana"},{"birdId":"bcnher","commonName":"Black-crowned Night Heron","sciName":"Nycticorax nycticorax"},{"birdId":"belkin1","commonName":"Belted Kingfisher","sciName":"Megaceryle alcyon"},{"birdId":"bfoboo","commonName":"Blue-footed Booby","sciName":"Sula nebouxii"},{"birdId":"brnnod","commonName":"Brown Noddy","sciName":"Anous stolidus"},{"birdId":"blkter","commonName":"Black Tern","sciName":"Chlidonias niger"},{"birdId":"solsan","commonName":"Solitary Sandpiper","sciName":"Tringa solitaria"},{"birdId":"btnwar","commonName":"Black-throated Green Warbler","sciName":"Setophaga virens"},{"birdId":"vigswa","commonName":"Violet-green Swallow","sciName":"Tachycineta thalassina"},{"birdId":"bobher1","commonName":"Boat-billed Heron","sciName":"Cochlearius cochlearius"},{"birdId":"belvir","commonName":"Bell's Vireo","sciName":"Vireo bellii"},{"birdId":"cliswa","commonName":"Cliff Swallow","sciName":"Petrochelidon pyrrhonota"},{"birdId":"rethaw","commonName":"Red-tailed Hawk","sciName":"Buteo jamaicensis"},{"birdId":"wewpew","commonName":"Western Wood-Pewee","sciName":"Contopus sordidulus"},{"birdId":"swathr","commonName":"Swainson's Thrush","sciName":"Catharus ustulatus"},{"birdId":"reevir1","commonName":"Red-eyed Vireo","sciName":"Vireo olivaceus"},{"birdId":"comyel","commonName":"Common Yellowthroat","sciName":"Geothlypis trichas"},{"birdId":"camwar","commonName":"Cape May Warbler","sciName":"Setophaga tigrina"},{"birdId":"amgplo","commonName":"American Golden-Plover","sciName":"Pluvialis dominica"},{"birdId":"pasowl4","commonName":"Pacific Screech-Owl","sciName":"Megascops cooperi"},{"birdId":"pibgre","commonName":"Pied-billed Grebe","sciName":"Podilymbus podiceps"},{"birdId":"hrshaw","commonName":"Harris's Hawk","sciName":"Parabuteo unicinctus"},{"birdId":"yebcha","commonName":"Yellow-breasted Chat","sciName":"Icteria virens"},{"birdId":"olsfly","commonName":"Olive-sided Flycatcher","sciName":"Contopus cooperi"},{"birdId":"brnowl","commonName":"Barn Owl","sciName":"Tyto alba"},{"birdId":"ribgul","commonName":"Ring-billed Gull","sciName":"Larus delawarensis"},{"birdId":"hergul","commonName":"Herring Gull","sciName":"Larus argentatus"},{"birdId":"forter","commonName":"Forster's Tern","sciName":"Sterna forsteri"},{"birdId":"grbhaw1","commonName":"Great Black Hawk","sciName":"Buteogallus urubitinga"},{"birdId":"lyhvul1","commonName":"Lesser Yellow-headed Vulture","sciName":"Cathartes burrovianus"},{"birdId":"rudcra1","commonName":"Ruddy Crake","sciName":"Laterallus ruber"},{"birdId":"hofwoo1","commonName":"Hoffmann's Woodpecker","sciName":"Melanerpes hoffmannii"},{"birdId":"whrsan","commonName":"White-rumped Sandpiper","sciName":"Calidris fuscicollis"},{"birdId":"crahaw","commonName":"Crane Hawk","sciName":"Geranospiza caerulescens"},{"birdId":"ampkin1","commonName":"American Pygmy Kingfisher","sciName":"Chloroceryle aenea"},{"birdId":"chcswi1","commonName":"Chestnut-collared Swift","sciName":"Streptoprocne rutila"},{"birdId":"brratt1","commonName":"Bright-rumped Attila","sciName":"Attila spadiceus"},{"birdId":"redpha1","commonName":"Red Phalarope","sciName":"Phalaropus fulicarius"},{"birdId":"bkspet","commonName":"Black Storm-Petrel","sciName":"Hydrobates melania"},{"birdId":"lsspet","commonName":"Least Storm-Petrel","sciName":"Hydrobates microsoma"},{"birdId":"briter1","commonName":"Bridled Tern","sciName":"Onychoprion anaethetus"},{"birdId":"whtkit","commonName":"White-tailed Kite","sciName":"Elanus leucurus"},{"birdId":"pomjae","commonName":"Pomarine Jaeger","sciName":"Stercorarius pomarinus"},{"birdId":"shshaw","commonName":"Sharp-shinned Hawk","sciName":"Accipiter striatus"},{"birdId":"dunlin","commonName":"Dunlin","sciName":"Calidris alpina"},{"birdId":"woewar1","commonName":"Worm-eating Warbler","sciName":"Helmitheros vermivorum"},{"birdId":"cavswa","commonName":"Cave Swallow","sciName":"Petrochelidon fulva"},{"birdId":"grhkit1","commonName":"Gray-headed Kite","sciName":"Leptodon cayanensis"},{"birdId":"blkswi","commonName":"Black Swift","sciName":"Cypseloides niger"},{"birdId":"yebcuc","commonName":"Yellow-billed Cuckoo","sciName":"Coccyzus americanus"},{"birdId":"greela","commonName":"Greenish Elaenia","sciName":"Myiopagis viridicata"},{"birdId":"mouwar","commonName":"Mourning Warbler","sciName":"Geothlypis philadelphia"},{"birdId":"motowl","commonName":"Mottled Owl","sciName":"Strix virgata"},{"birdId":"snoplo5","commonName":"Snowy Plover","sciName":"Anarhynchus nivosus"},{"birdId":"renpha","commonName":"Red-necked Phalarope","sciName":"Phalaropus lobatus"},{"birdId":"thitin1","commonName":"Thicket Tinamou","sciName":"Crypturellus cinnamomeus"},{"birdId":"lesroa1","commonName":"Lesser Roadrunner","sciName":"Geococcyx velox"},{"birdId":"bltgol1","commonName":"Blue-throated Goldentail","sciName":"Chlorestes eliciae"},{"birdId":"kinvul1","commonName":"King Vulture","sciName":"Sarcoramphus papa"},{"birdId":"dotkit1","commonName":"Double-toothed Kite","sciName":"Harpagus bidentatus"},{"birdId":"whthaw","commonName":"White-tailed Hawk","sciName":"Geranoaetus albicaudatus"},{"birdId":"pabwoo1","commonName":"Pale-billed Woodpecker","sciName":"Campephilus guatemalensis"},{"birdId":"lotman1","commonName":"Long-tailed Manakin","sciName":"Chiroxiphia linearis"},{"birdId":"phivir","commonName":"Philadelphia Vireo","sciName":"Vireo philadelphicus"},{"birdId":"rocwre","commonName":"Rock Wren","sciName":"Salpinctes obsoletus"},{"birdId":"cedwax","commonName":"Cedar Waxwing","sciName":"Bombycilla cedrorum"},{"birdId":"gycyel","commonName":"Gray-crowned Yellowthroat","sciName":"Geothlypis poliocephala"},{"birdId":"macwar","commonName":"MacGillivray's Warbler","sciName":"Geothlypis tolmiei"},{"birdId":"hoowar","commonName":"Hooded Warbler","sciName":"Setophaga citrina"},{"birdId":"rcatan1","commonName":"Red-crowned Ant-Tanager","sciName":"Habia rubica"},{"birdId":"blubun","commonName":"Blue Bunting","sciName":"Cyanocompsa parellina"},{"birdId":"yenpar1","commonName":"Yellow-naped Parrot","sciName":"Amazona auropalliata"}]