[{"birdId":"mutswa","commonName":"Mute Swan","sciName":"Cygnus olor"},{"birdId":"laudov1","commonName":"Laughing Dove","sciName":"Spilopelia senegalensis"},{"birdId":"commyn","commonName":"Common Myna","sciName":"Acridotheres tristis"},{"birdId":"houspa","commonName":"House Sparrow","sciName":"Passer domesticus"},{"birdId":"eutspa","commonName":"Eurasian Tree Sparrow","sciName":"Passer montanus"},{"birdId":"whiwag","commonName":"White Wagtail","sciName":"Motacilla alba"},{"birdId":"barswa","commonName":"Barn Swallow","sciName":"Hirundo rustica"},{"birdId":"desfin2","commonName":"Desert Finch","sciName":"Rhodospiza obsoleta"},{"birdId":"aspfly1","commonName":"Indian Paradise-Flycatcher","sciName":"Terpsiphone paradisi"},{"birdId":"eurrol1","commonName":"European Roller","sciName":"Coracias garrulus"},{"birdId":"grywag","commonName":"Gray Wagtail","sciName":"Motacilla cinerea"},{"birdId":"leskes1","commonName":"Lesser Kestrel","sciName":"Falco naumanni"},{"birdId":"eurwar1","commonName":"Common Reed Warbler","sciName":"Acrocephalus scirpaceus"},{"birdId":"mewgul","commonName":"Common Gull","sciName":"Larus canus"},{"birdId":"caster1","commonName":"Caspian Tern","sciName":"Hydroprogne caspia"},{"birdId":"graher1","commonName":"Gray Heron","sciName":"Ardea cinerea"},{"birdId":"eurgri1","commonName":"Eurasian Griffon","sciName":"Gyps fulvus"},{"birdId":"wemhar1","commonName":"Western Marsh Harrier","sciName":"Circus aeruginosus"},{"birdId":"bcbeat1","commonName":"Blue-cheeked Bee-eater","sciName":"Merops persicus"},{"birdId":"rinphe1","commonName":"Ring-necked Pheasant","sciName":"Phasianus colchicus"},{"birdId":"shikra1","commonName":"Shikra","sciName":"Accipiter badius"},{"birdId":"eurmag1","commonName":"Eurasian Magpie","sciName":"Pica pica"},{"birdId":"rook1","commonName":"Rook","sciName":"Corvus frugilegus"},{"birdId":"blrwar1","commonName":"Blyth's Reed Warbler","sciName":"Acrocephalus dumetorum"},{"birdId":"comcuc","commonName":"Common Cuckoo","sciName":"Cuculus canorus"},{"birdId":"bkwsti","commonName":"Black-winged Stilt","sciName":"Himantopus himantopus"},{"birdId":"lirplo","commonName":"Little Ringed Plover","sciName":"Charadrius dubius"},{"birdId":"whtlap1","commonName":"White-tailed Lapwing","sciName":"Vanellus leucurus"},{"birdId":"eurjac","commonName":"Eurasian Jackdaw","sciName":"Corvus monedula"},{"birdId":"crelar1","commonName":"Crested Lark","sciName":"Galerida cristata"},{"birdId":"pasmar1","commonName":"Pale Martin","sciName":"Riparia diluta"},{"birdId":"piebus1","commonName":"Pied Bushchat","sciName":"Saxicola caprata"},{"birdId":"eaywag1","commonName":"Western Yellow Wagtail","sciName":"Motacilla flava"},{"birdId":"citwag","commonName":"Citrine Wagtail","sciName":"Motacilla citreola"},{"birdId":"lolbuz1","commonName":"Long-legged Buzzard","sciName":"Buteo rufinus"},{"birdId":"eubeat1","commonName":"European Bee-eater","sciName":"Merops apiaster"},{"birdId":"cowpig1","commonName":"Common Wood-Pigeon","sciName":"Columba palumbus"},{"birdId":"whisto1","commonName":"White Stork","sciName":"Ciconia ciconia"},{"birdId":"carcro1","commonName":"Carrion Crow","sciName":"Corvus corone"},{"birdId":"eucdov","commonName":"Eurasian Collared-Dove","sciName":"Streptopelia decaocto"},{"birdId":"osprey","commonName":"Osprey","sciName":"Pandion haliaetus"},{"birdId":"eurspa1","commonName":"Eurasian Sparrowhawk","sciName":"Accipiter nisus"},{"birdId":"eurkes","commonName":"Eurasian Kestrel","sciName":"Falco tinnunculus"},{"birdId":"eursta","commonName":"European Starling","sciName":"Sturnus vulgaris"},{"birdId":"rudshe","commonName":"Ruddy Shelduck","sciName":"Tadorna ferruginea"},{"birdId":"recpoc","commonName":"Red-crested Pochard","sciName":"Netta rufina"},{"birdId":"renpha","commonName":"Red-necked Phalarope","sciName":"Phalaropus lobatus"},{"birdId":"litowl1","commonName":"Little Owl","sciName":"Athene noctua"},{"birdId":"comrav","commonName":"Common Raven","sciName":"Corvus corax"},{"birdId":"kenplo1","commonName":"Kentish Plover","sciName":"Anarhynchus alexandrinus"},{"birdId":"colpra","commonName":"Collared Pratincole","sciName":"Glareola pratincola"},{"birdId":"comter","commonName":"Common Tern","sciName":"Sterna hirundo"},{"birdId":"purher1","commonName":"Purple Heron","sciName":"Ardea purpurea"},{"birdId":"sykwar2","commonName":"Sykes's Warbler","sciName":"Iduna rama"},{"birdId":"clrwar1","commonName":"Clamorous Reed Warbler","sciName":"Acrocephalus stentoreus"},{"birdId":"banswa","commonName":"Bank Swallow","sciName":"Riparia riparia"},{"birdId":"rutscr1","commonName":"Rufous-tailed Scrub-Robin","sciName":"Cercotrichas galactotes"},{"birdId":"alpswi1","commonName":"Alpine Swift","sciName":"Tachymarptis melba"},{"birdId":"comswi","commonName":"Common Swift","sciName":"Apus apus"},{"birdId":"gargan","commonName":"Garganey","sciName":"Spatula querquedula"},{"birdId":"rerswa1","commonName":"Red-rumped Swallow","sciName":"Cecropis daurica"},{"birdId":"rocpig","commonName":"Rock Pigeon","sciName":"Columba livia"},{"birdId":"trepip","commonName":"Tree Pipit","sciName":"Anthus trivialis"},{"birdId":"corbun1","commonName":"Corn Bunting","sciName":"Emberiza calandra"},{"birdId":"tstlar1","commonName":"Turkestan Short-toed Lark","sciName":"Alaudala heinei"},{"birdId":"norhar1","commonName":"Hen Harrier","sciName":"Circus cyaneus"},{"birdId":"mallar3","commonName":"Mallard","sciName":"Anas platyrhynchos"},{"birdId":"watrai1","commonName":"Water Rail","sciName":"Rallus aquaticus"},{"birdId":"steeag1","commonName":"Steppe Eagle","sciName":"Aquila nipalensis"},{"birdId":"bearee1","commonName":"Bearded Reedling","sciName":"Panurus biarmicus"},{"birdId":"gnwtea","commonName":"Green-winged Teal","sciName":"Anas crecca"},{"birdId":"hoocro1","commonName":"Hooded Crow","sciName":"Corvus cornix"},{"birdId":"eurbla","commonName":"Eurasian Blackbird","sciName":"Turdus merula"},{"birdId":"fieldf","commonName":"Fieldfare","sciName":"Turdus pilaris"},{"birdId":"datthr1","commonName":"Black-throated Thrush","sciName":"Turdus atrogularis"},{"birdId":"eurrob1","commonName":"European Robin","sciName":"Erithacus rubecula"},{"birdId":"comcha","commonName":"Common Chaffinch","sciName":"Fringilla coelebs"},{"birdId":"brambl","commonName":"Brambling","sciName":"Fringilla montifringilla"},{"birdId":"goleag","commonName":"Golden Eagle","sciName":"Aquila chrysaetos"},{"birdId":"greegr","commonName":"Great Egret","sciName":"Ardea alba"},{"birdId":"gretit1","commonName":"Great Tit","sciName":"Parus major"},{"birdId":"hoopoe","commonName":"Eurasian Hoopoe","sciName":"Upupa epops"},{"birdId":"blakit1","commonName":"Black Kite","sciName":"Milvus migrans"},{"birdId":"whteag","commonName":"White-tailed Eagle","sciName":"Haliaeetus albicilla"},{"birdId":"piewhe1","commonName":"Pied Wheatear","sciName":"Oenanthe pleschanka"},{"birdId":"grecor","commonName":"Great Cormorant","sciName":"Phalacrocorax carbo"},{"birdId":"casgul2","commonName":"Caspian Gull","sciName":"Larus cachinnans"},{"birdId":"commoo3","commonName":"Eurasian Moorhen","sciName":"Gallinula chloropus"},{"birdId":"comsni","commonName":"Common Snipe","sciName":"Gallinago gallinago"},{"birdId":"comsan","commonName":"Common Sandpiper","sciName":"Actitis hypoleucos"},{"birdId":"grnsan","commonName":"Green Sandpiper","sciName":"Tringa ochropus"},{"birdId":"woosan","commonName":"Wood Sandpiper","sciName":"Tringa glareola"},{"birdId":"rudtur","commonName":"Ruddy Turnstone","sciName":"Arenaria interpres"},{"birdId":"ruff","commonName":"Ruff","sciName":"Calidris pugnax"},{"birdId":"litsti","commonName":"Little Stint","sciName":"Calidris minuta"},{"birdId":"gloibi","commonName":"Glossy Ibis","sciName":"Plegadis falcinellus"},{"birdId":"deslar1","commonName":"Desert Lark","sciName":"Ammomanes deserti"},{"birdId":"spofly1","commonName":"Spotted Flycatcher","sciName":"Muscicapa striata"},{"birdId":"blbsan1","commonName":"Black-bellied Sandgrouse","sciName":"Pterocles orientalis"},{"birdId":"grsplo","commonName":"Greater Sand-Plover","sciName":"Anarhynchus leschenaultii"},{"birdId":"slbgul1","commonName":"Slender-billed Gull","sciName":"Chroicocephalus genei"},{"birdId":"litter1","commonName":"Little Tern","sciName":"Sternula albifrons"},{"birdId":"gubter2","commonName":"Gull-billed Tern","sciName":"Gelochelidon nilotica"},{"birdId":"horlar","commonName":"Horned Lark","sciName":"Eremophila alpestris"},{"birdId":"chukar","commonName":"Chukar","sciName":"Alectoris chukar"},{"birdId":"egyvul1","commonName":"Egyptian Vulture","sciName":"Neophron percnopterus"},{"birdId":"cinvul1","commonName":"Cinereous Vulture","sciName":"Aegypius monachus"},{"birdId":"rebshr1","commonName":"Red-backed Shrike","sciName":"Lanius collurio"},{"birdId":"gstlar1","commonName":"Greater Short-toed Lark","sciName":"Calandrella brachydactyla"},{"birdId":"grewar3","commonName":"Greenish Warbler","sciName":"Phylloscopus trochiloides"},{"birdId":"stswar1","commonName":"Scrub Warbler","sciName":"Scotocerca inquieta"},{"birdId":"leswhi4","commonName":"Lesser Whitethroat","sciName":"Curruca curruca"},{"birdId":"grewhi1","commonName":"Greater Whitethroat","sciName":"Curruca communis"},{"birdId":"pernut1","commonName":"Eastern Rock Nuthatch","sciName":"Sitta tephronota"},{"birdId":"thrnig1","commonName":"Thrush Nightingale","sciName":"Luscinia luscinia"},{"birdId":"blared1","commonName":"Black Redstart","sciName":"Phoenicurus ochruros"},{"birdId":"isawhe1","commonName":"Isabelline Wheatear","sciName":"Oenanthe isabellina"},{"birdId":"finwhe1","commonName":"Finsch's Wheatear","sciName":"Oenanthe finschii"},{"birdId":"tawpip1","commonName":"Tawny Pipit","sciName":"Anthus campestris"},{"birdId":"rehbun1","commonName":"Red-headed Bunting","sciName":"Emberiza bruniceps"},{"birdId":"isashr1","commonName":"Isabelline Shrike","sciName":"Lanius isabellinus"},{"birdId":"rutshr2","commonName":"Red-tailed Shrike","sciName":"Lanius phoenicuroides"},{"birdId":"legshr2","commonName":"Lesser Gray Shrike","sciName":"Lanius minor"},{"birdId":"comred2","commonName":"Common Redstart","sciName":"Phoenicurus phoenicurus"},{"birdId":"deswhe1","commonName":"Desert Wheatear","sciName":"Oenanthe deserti"},{"birdId":"gyhbun1","commonName":"Gray-necked Bunting","sciName":"Emberiza buchanani"},{"birdId":"eaowar1","commonName":"Eastern Olivaceous Warbler","sciName":"Iduna pallida"},{"birdId":"norsho","commonName":"Northern Shoveler","sciName":"Spatula clypeata"},{"birdId":"temsti","commonName":"Temminck's Stint","sciName":"Calidris temminckii"},{"birdId":"whiter2","commonName":"Whiskered Tern","sciName":"Chlidonias hybrida"},{"birdId":"blkter","commonName":"Black Tern","sciName":"Chlidonias niger"},{"birdId":"grebit1","commonName":"Great Bittern","sciName":"Botaurus stellaris"},{"birdId":"mouwar1","commonName":"Moustached Warbler","sciName":"Acrocephalus melanopogon"},{"birdId":"savwar1","commonName":"Savi's Warbler","sciName":"Locustella luscinioides"},{"birdId":"rossta2","commonName":"Rosy Starling","sciName":"Pastor roseus"},{"birdId":"palsan1","commonName":"Pallas's Sandgrouse","sciName":"Syrrhaptes paradoxus"},{"birdId":"menwar1","commonName":"Menetries's Warbler","sciName":"Curruca mystacea"},{"birdId":"comnig1","commonName":"Common Nightingale","sciName":"Luscinia megarhynchos"},{"birdId":"gadwal","commonName":"Gadwall","sciName":"Mareca strepera"},{"birdId":"martea1","commonName":"Marbled Duck","sciName":"Marmaronetta angustirostris"},{"birdId":"grcgre1","commonName":"Great Crested Grebe","sciName":"Podiceps cristatus"},{"birdId":"pieavo1","commonName":"Pied Avocet","sciName":"Recurvirostra avosetta"},{"birdId":"bkbplo","commonName":"Black-bellied Plover","sciName":"Pluvialis squatarola"},{"birdId":"spored","commonName":"Spotted Redshank","sciName":"Tringa erythropus"},{"birdId":"cursan","commonName":"Curlew Sandpiper","sciName":"Calidris ferruginea"},{"birdId":"dunlin","commonName":"Dunlin","sciName":"Calidris alpina"},{"birdId":"bkhgul","commonName":"Black-headed Gull","sciName":"Chroicocephalus ridibundus"},{"birdId":"lbbgul","commonName":"Lesser Black-backed Gull","sciName":"Larus fuscus"},{"birdId":"eurspo1","commonName":"Eurasian Spoonbill","sciName":"Platalea leucorodia"},{"birdId":"orisky1","commonName":"Oriental Skylark","sciName":"Alauda gulgula"},{"birdId":"comchi1","commonName":"Common Chiffchaff","sciName":"Phylloscopus collybita"},{"birdId":"spaspa1","commonName":"Spanish Sparrow","sciName":"Passer hispaniolensis"},{"birdId":"eutdov","commonName":"European Turtle-Dove","sciName":"Streptopelia turtur"},{"birdId":"comkin1","commonName":"Common Kingfisher","sciName":"Alcedo atthis"},{"birdId":"padwar1","commonName":"Paddyfield Warbler","sciName":"Acrocephalus agricola"},{"birdId":"shteag1","commonName":"Short-toed Snake-Eagle","sciName":"Circaetus gallicus"},{"birdId":"eurcoo","commonName":"Eurasian Coot","sciName":"Fulica atra"},{"birdId":"grwpel1","commonName":"Great White Pelican","sciName":"Pelecanus onocrotalus"},{"birdId":"lotshr1","commonName":"Long-tailed Shrike","sciName":"Lanius schach"},{"birdId":"sibsto1","commonName":"Siberian Stonechat","sciName":"Saxicola maurus"},{"birdId":"eurnig1","commonName":"Eurasian Nightjar","sciName":"Caprimulgus europaeus"},{"birdId":"egynig1","commonName":"Egyptian Nightjar","sciName":"Caprimulgus aegyptius"},{"birdId":"gragoo","commonName":"Graylag Goose","sciName":"Anser anser"},{"birdId":"litegr","commonName":"Little Egret","sciName":"Egretta garzetta"},{"birdId":"euhbuz1","commonName":"European Honey-buzzard","sciName":"Pernis apivorus"},{"birdId":"orihob2","commonName":"Oriental Honey-buzzard","sciName":"Pernis ptilorhynchus"},{"birdId":"eugori2","commonName":"Eurasian Golden Oriole","sciName":"Oriolus oriolus"},{"birdId":"tugjay1","commonName":"Turkestan Ground-Jay","sciName":"Podoces panderi"},{"birdId":"blueth","commonName":"Bluethroat","sciName":"Luscinia svecica"},{"birdId":"comros","commonName":"Common Rosefinch","sciName":"Carpodacus erythrinus"},{"birdId":"ortbun1","commonName":"Ortolan Bunting","sciName":"Emberiza hortulana"},{"birdId":"bcnher","commonName":"Black-crowned Night Heron","sciName":"Nycticorax nycticorax"},{"birdId":"comhom1","commonName":"Western House-Martin","sciName":"Delichon urbicum"},{"birdId":"comred1","commonName":"Common Redshank","sciName":"Tringa totanus"},{"birdId":"rocpet1","commonName":"Rock Sparrow","sciName":"Petronia petronia"},{"birdId":"corplo","commonName":"Common Ringed Plover","sciName":"Charadrius hiaticula"},{"birdId":"norwhe","commonName":"Northern Wheatear","sciName":"Oenanthe oenanthe"},{"birdId":"marsan","commonName":"Marsh Sandpiper","sciName":"Tringa stagnatilis"},{"birdId":"litgre1","commonName":"Little Grebe","sciName":"Tachybaptus ruficollis"},{"birdId":"gwfgoo","commonName":"Greater White-fronted Goose","sciName":"Anser albifrons"},{"birdId":"bktgod","commonName":"Black-tailed Godwit","sciName":"Limosa limosa"},{"birdId":"dalpel1","commonName":"Dalmatian Pelican","sciName":"Pelecanus crispus"},{"birdId":"compoc","commonName":"Common Pochard","sciName":"Aythya ferina"},{"birdId":"ortdov","commonName":"Oriental Turtle-Dove","sciName":"Streptopelia orientalis"},{"birdId":"comgre","commonName":"Common Greenshank","sciName":"Tringa nebularia"},{"birdId":"bimlar1","commonName":"Bimaculated Lark","sciName":"Melanocorypha bimaculata"},{"birdId":"combuz1","commonName":"Common Buzzard","sciName":"Buteo buteo"},{"birdId":"pygcor2","commonName":"Pygmy Cormorant","sciName":"Microcarbo pygmaeus"},{"birdId":"eurgol","commonName":"European Goldfinch","sciName":"Carduelis carduelis"},{"birdId":"tufduc","commonName":"Tufted Duck","sciName":"Aythya fuligula"},{"birdId":"gbhgul2","commonName":"Pallas's Gull","sciName":"Ichthyaetus ichthyaetus"},{"birdId":"demcra1","commonName":"Demoiselle Crane","sciName":"Anthropoides virgo"},{"birdId":"merlin","commonName":"Merlin","sciName":"Falco columbarius"},{"birdId":"callar1","commonName":"Calandra Lark","sciName":"Melanocorypha calandra"},{"birdId":"norshr1","commonName":"Great Gray Shrike","sciName":"Lanius excubitor"},{"birdId":"comshe","commonName":"Common Shelduck","sciName":"Tadorna tadorna"},{"birdId":"smew","commonName":"Smew","sciName":"Mergellus albellus"},{"birdId":"norpin","commonName":"Northern Pintail","sciName":"Anas acuta"},{"birdId":"comgol","commonName":"Common Goldeneye","sciName":"Bucephala clangula"},{"birdId":"norlap","commonName":"Northern Lapwing","sciName":"Vanellus vanellus"},{"birdId":"rubred2","commonName":"Rufous-backed Redstart","sciName":"Phoenicurus erythronotus"},{"birdId":"eurlin1","commonName":"Eurasian Linnet","sciName":"Linaria cannabina"},{"birdId":"pinbun","commonName":"Pine Bunting","sciName":"Emberiza leucocephalos"},{"birdId":"reebun","commonName":"Reed Bunting","sciName":"Emberiza schoeniclus"},{"birdId":"commer","commonName":"Common Merganser","sciName":"Mergus merganser"},{"birdId":"cetwar1","commonName":"Cetti's Warbler","sciName":"Cettia cetti"},{"birdId":"goldcr1","commonName":"Goldcrest","sciName":"Regulus regulus"},{"birdId":"skylar","commonName":"Eurasian Skylark","sciName":"Alauda arvensis"},{"birdId":"watpip1","commonName":"Water Pipit","sciName":"Anthus spinoletta"},{"birdId":"eurhob","commonName":"Eurasian Hobby","sciName":"Falco subbuteo"},{"birdId":"palhar1","commonName":"Pallid Harrier","sciName":"Circus macrourus"},{"birdId":"eurcur","commonName":"Eurasian Curlew","sciName":"Numenius arquata"},{"birdId":"batgod","commonName":"Bar-tailed Godwit","sciName":"Limosa lapponica"},{"birdId":"twite1","commonName":"Twite","sciName":"Linaria flavirostris"},{"birdId":"tersan","commonName":"Terek Sandpiper","sciName":"Xenus cinereus"},{"birdId":"brnrav1","commonName":"Brown-necked Raven","sciName":"Corvus ruficollis"},{"birdId":"monhar1","commonName":"Montagu's Harrier","sciName":"Circus pygargus"},{"birdId":"macbus1","commonName":"Macqueen's Bustard","sciName":"Chlamydotis macqueenii"},{"birdId":"eutkne1","commonName":"Eurasian Thick-knee","sciName":"Burhinus oedicnemus"},{"birdId":"blasto1","commonName":"Black Stork","sciName":"Ciconia nigra"},{"birdId":"eurwig","commonName":"Eurasian Wigeon","sciName":"Mareca penelope"},{"birdId":"booeag1","commonName":"Booted Eagle","sciName":"Hieraaetus pennatus"},{"birdId":"boowar1","commonName":"Booted Warbler","sciName":"Iduna caligata"},{"birdId":"asdwar1","commonName":"Asian Desert Warbler","sciName":"Curruca nana"},{"birdId":"barwar1","commonName":"Barred Warbler","sciName":"Curruca nisoria"},{"birdId":"eaowar2","commonName":"Eastern Orphean Warbler","sciName":"Curruca crassirostris"},{"birdId":"rtrthr1","commonName":"Rufous-tailed Rock-Thrush","sciName":"Monticola saxatilis"},{"birdId":"ferduc","commonName":"Ferruginous Duck","sciName":"Aythya nyroca"},{"birdId":"litbit1","commonName":"Little Bittern","sciName":"Ixobrychus minutus"},{"birdId":"burthr","commonName":"Blue Rock-Thrush","sciName":"Monticola solitarius"},{"birdId":"monfin2","commonName":"Mongolian Finch","sciName":"Bucanetes mongolicus"},{"birdId":"impeag1","commonName":"Imperial Eagle","sciName":"Aquila heliaca"},{"birdId":"wlwwar","commonName":"Willow Warbler","sciName":"Phylloscopus trochilus"},{"birdId":"varwhe1","commonName":"Variable Wheatear","sciName":"Oenanthe picata"},{"birdId":"trufin2","commonName":"Trumpeter Finch","sciName":"Bucanetes githagineus"},{"birdId":"comqua1","commonName":"Common Quail","sciName":"Coturnix coturnix"},{"birdId":"eurwry","commonName":"Eurasian Wryneck","sciName":"Jynx torquilla"},{"birdId":"comcra","commonName":"Common Crane","sciName":"Grus grus"},{"birdId":"blwpra1","commonName":"Black-winged Pratincole","sciName":"Glareola nordmanni"},{"birdId":"grefla3","commonName":"Greater Flamingo","sciName":"Phoenicopterus roseus"},{"birdId":"euroys1","commonName":"Eurasian Oystercatcher","sciName":"Haematopus ostralegus"},{"birdId":"wcptit1","commonName":"White-crowned Penduline-Tit","sciName":"Remiz coronatus"},{"birdId":"spocra1","commonName":"Spotted Crake","sciName":"Porzana porzana"},{"birdId":"litbus1","commonName":"Little Bustard","sciName":"Tetrax tetrax"},{"birdId":"rebfly","commonName":"Red-breasted Flycatcher","sciName":"Ficedula parva"},{"birdId":"eueowl1","commonName":"Eurasian Eagle-Owl","sciName":"Bubo bubo"},{"birdId":"euptit1","commonName":"Eurasian Penduline-Tit","sciName":"Remiz pendulinus"},{"birdId":"loeowl","commonName":"Long-eared Owl","sciName":"Asio otus"},{"birdId":"jacsni","commonName":"Jack Snipe","sciName":"Lymnocryptes minimus"},{"birdId":"perfal","commonName":"Peregrine Falcon","sciName":"Falco peregrinus"},{"birdId":"lammer1","commonName":"Bearded Vulture","sciName":"Gypaetus barbatus"},{"birdId":"bltacc1","commonName":"Black-throated Accentor","sciName":"Prunella atrogularis"},{"birdId":"fifser1","commonName":"Fire-fronted Serin","sciName":"Serinus pusillus"},{"birdId":"rebmer","commonName":"Red-breasted Merganser","sciName":"Mergus serrator"},{"birdId":"wallcr1","commonName":"Wallcreeper","sciName":"Tichodroma muraria"},{"birdId":"whhduc1","commonName":"White-headed Duck","sciName":"Oxyura leucocephala"},{"birdId":"himgri1","commonName":"Himalayan Griffon","sciName":"Gyps himalayensis"},{"birdId":"grseag1","commonName":"Greater Spotted Eagle","sciName":"Clanga clanga"},{"birdId":"lstlar2","commonName":"Asian Short-toed Lark","sciName":"Alaudala cheleensis"},{"birdId":"pitsan1","commonName":"Pin-tailed Sandgrouse","sciName":"Pterocles alchata"},{"birdId":"sheowl","commonName":"Short-eared Owl","sciName":"Asio flammeus"},{"birdId":"soclap1","commonName":"Sociable Lapwing","sciName":"Vanellus gregarius"},{"birdId":"yellow2","commonName":"Yellowhammer","sciName":"Emberiza citrinella"},{"birdId":"whwlar1","commonName":"White-winged Lark","sciName":"Alauda leucoptera"},{"birdId":"meapip1","commonName":"Meadow Pipit","sciName":"Anthus pratensis"},{"birdId":"eargre","commonName":"Eared Grebe","sciName":"Podiceps nigricollis"},{"birdId":"whwter","commonName":"White-winged Tern","sciName":"Chlidonias leucopterus"},{"birdId":"whinch1","commonName":"Whinchat","sciName":"Saxicola rubetra"},{"birdId":"cogwar1","commonName":"Common Grasshopper Warbler","sciName":"Locustella naevia"},{"birdId":"eurcrm1","commonName":"Eurasian Crag-Martin","sciName":"Ptyonoprogne rupestris"},{"birdId":"lotjae","commonName":"Long-tailed Jaeger","sciName":"Stercorarius longicaudus"},{"birdId":"garwar1","commonName":"Garden Warbler","sciName":"Sylvia borin"},{"birdId":"upcwar1","commonName":"Upcher's Warbler","sciName":"Hippolais languida"},{"birdId":"whimbr","commonName":"Whimbrel","sciName":"Numenius phaeopus"},{"birdId":"rolhaw","commonName":"Rough-legged Hawk","sciName":"Buteo lagopus"},{"birdId":"stodov1","commonName":"Stock Dove","sciName":"Columba oenas"},{"birdId":"horgre","commonName":"Horned Grebe","sciName":"Podiceps auritus"},{"birdId":"rengre","commonName":"Red-necked Grebe","sciName":"Podiceps grisegena"},{"birdId":"sakfal1","commonName":"Saker Falcon","sciName":"Falco cherrug"}]